LICENSE
cfjson/__init__.py
cfjson/coder.py
cfjson/serde/__init__.py
cfjson/serde/datetime_serde.py
cfjson/serde/decimal_serde.py
cfjson/serde/pathlib_serde.py
cf_json-0.1.0.dist-info/LICENSE
cf_json-0.1.0.dist-info/WHEEL
cf_json-0.1.0.dist-info/METADATA
cf_json-0.1.0.dist-info/RECORD
