Metadata-Version: 2.1
Name: cf-json
Version: 0.1.0
Summary: JSON with extensions to support serialization for common types
Home-page: https://cf-json.readthedocs.io/en/latest/quickstart.html
License: MIT
Author: Keir Rice
Author-email: keir@clayfox.co.nz
Requires-Python: >=3.6,<4.0
Classifier: License :: OSI Approved :: MIT License
Classifier: Operating System :: OS Independent
Classifier: Programming Language :: Python :: 3
Classifier: Programming Language :: Python :: 3.6
Classifier: Programming Language :: Python :: 3.7
Classifier: Programming Language :: Python :: 3.8
Classifier: Programming Language :: Python :: 3.9
Classifier: Topic :: Software Development :: Libraries :: Python Modules
Requires-Dist: python-dateutil (>=2.8,<2.9); python_version < "3.7"
Project-URL: Bug Tracker, https://gitlab.clayfox.co.nz/cf/cf-json/-/issues
Project-URL: Documentation, https://cf-json.readthedocs.io/en/latest/
Project-URL: Repository, https://gitlab.clayfox.co.nz/cf/cf-json
